aliyunsdkoos/__init__.py
aliyunsdkoos/endpoint.py
aliyunsdkoos/request/__init__.py
aliyunsdkoos/request/v20190601/AnalyzeGitRepositoryRequest.py
aliyunsdkoos/request/v20190601/CancelExecutionRequest.py
aliyunsdkoos/request/v20190601/ChangeResourceGroupRequest.py
aliyunsdkoos/request/v20190601/ContinueDeployApplicationGroupRequest.py
aliyunsdkoos/request/v20190601/CreateApplicationGroupRequest.py
aliyunsdkoos/request/v20190601/CreateApplicationRequest.py
aliyunsdkoos/request/v20190601/CreateOpsItemRequest.py
aliyunsdkoos/request/v20190601/CreateParameterRequest.py
aliyunsdkoos/request/v20190601/CreatePatchBaselineRequest.py
aliyunsdkoos/request/v20190601/CreateSecretParameterRequest.py
aliyunsdkoos/request/v20190601/CreateStateConfigurationRequest.py
aliyunsdkoos/request/v20190601/CreateTemplateRequest.py
aliyunsdkoos/request/v20190601/DeleteApplicationGroupRequest.py
aliyunsdkoos/request/v20190601/DeleteApplicationRequest.py
aliyunsdkoos/request/v20190601/DeleteExecutionsRequest.py
aliyunsdkoos/request/v20190601/DeleteParameterRequest.py
aliyunsdkoos/request/v20190601/DeletePatchBaselineRequest.py
aliyunsdkoos/request/v20190601/DeleteSecretParameterRequest.py
aliyunsdkoos/request/v20190601/DeleteStateConfigurationsRequest.py
aliyunsdkoos/request/v20190601/DeleteTemplateRequest.py
aliyunsdkoos/request/v20190601/DeleteTemplatesRequest.py
aliyunsdkoos/request/v20190601/DeployApplicationGroupRequest.py
aliyunsdkoos/request/v20190601/DescribeApplicationGroupBillRequest.py
aliyunsdkoos/request/v20190601/DescribeRegionsRequest.py
aliyunsdkoos/request/v20190601/GenerateExecutionPolicyRequest.py
aliyunsdkoos/request/v20190601/GenerateOpsItemRequest.py
aliyunsdkoos/request/v20190601/GetApplicationGroupRequest.py
aliyunsdkoos/request/v20190601/GetApplicationRequest.py
aliyunsdkoos/request/v20190601/GetExecutionTemplateRequest.py
aliyunsdkoos/request/v20190601/GetInventorySchemaRequest.py
aliyunsdkoos/request/v20190601/GetOpsItemRequest.py
aliyun_python_sdk_oos-1.5.16.dist-info/LICENSE
aliyun_python_sdk_oos-1.5.16.dist-info/METADATA
aliyun_python_sdk_oos-1.5.16.dist-info/WHEEL
aliyun_python_sdk_oos-1.5.16.dist-info/top_level.txt
aliyun_python_sdk_oos-1.5.16.dist-info/RECORD
